{
  "$type": "FeatureDefinitionFeatureSet, Assembly-CSharp",
  "featureSet": [
    "Definition:ActionAffinityWeaponMasteryToggle:de43d4da-8e63-50ad-a60b-8336602da181",
    "Definition:FeatureWeaponMasterySlow:656ecf35-2c95-593d-a1b4-96f4b4b245c2"
  ],
  "mode": "Union",
  "ancestryDamageTypeMap": [],
  "ancestryType": "Sorcerer",
  "defaultSelection": 0,
  "uniqueChoices": false,
  "enumerateInDescription": false,
  "hasRacialAffinity": false,
  "guiPresentation": {
    "$type": "GuiPresentation, Assembly-CSharp",
    "hidden": true,
    "title": "Feature/&NoContentTitle",
    "description": "Feature/&NoContentTitle",
    "spriteReference": {
      "$type": "UnityEngine.AddressableAssets.AssetReferenceSprite, Unity.Addressables",
      "m_AssetGUID": "",
      "m_SubObjectName": null,
      "m_SubObjectType": null
    },
    "color": {
      "$type": "UnityEngine.Color, UnityEngine.CoreModule",
      "r": 1.0,
      "g": 1.0,
      "b": 1.0,
      "a": 1.0
    },
    "symbolChar": "221E",
    "sortOrder": 0,
    "unusedInSolastaCOTM": false,
    "usedInValleyDLC": false
  },
  "contentCopyright": "UserContent",
  "guid": "1aeeb7a5-abc2-54f9-a671-744ae522ddd2",
  "contentPack": 9999,
  "name": "FeatureSetWeaponMasteryClubType"
}