{
  "$type": "SolastaUnfinishedBusiness.CustomDefinitions.CustomFightingStyleDefinition, SolastaUnfinishedBusiness",
  "features": [
    "Definition:OnComputeAttackModifierFightingStyleReactionary:893dfd7a-5355-5128-8752-675e52a6698f"
  ],
  "condition": "RangedWeaponAttack",
  "guiPresentation": {
    "$type": "GuiPresentation, Assembly-CSharp",
    "hidden": false,
    "title": "FightingStyle/&ReactionaryTitle",
    "description": "FightingStyle/&ReactionaryDescription",
    "spriteReference": {
      "$type": "UnityEngine.AddressableAssets.AssetReferenceSprite, Unity.Addressables",
      "m_AssetGUID": "aa99d934a7dfe064191c9a18e4822595",
      "m_SubObjectName": "Barbarian_Path_Berserker",
      "m_SubObjectType": "UnityEngine.Sprite, UnityEngine.CoreModule, Version=0.0.0.0, Culture=neutral, PublicKeyToken=null"
    },
    "color": {
      "$type": "UnityEngine.Color, UnityEngine.CoreModule",
      "r": 1.0,
      "g": 1.0,
      "b": 1.0,
      "a": 1.0
    },
    "symbolChar": "221E",
    "sortOrder": 0,
    "unusedInSolastaCOTM": false,
    "usedInValleyDLC": false
  },
  "contentCopyright": "UserContent",
  "guid": "7749242a-80b9-5a3f-9286-48ea3fa91968",
  "contentPack": 9999,
  "name": "Reactionary"
}