{
  "$type": "ItemDefinition, Assembly-CSharp",
  "inDungeonEditor": true,
  "merchantCategory": "MagicDevice",
  "weight": 2.0,
  "slotTypes": [
    "UtilitySlot",
    "ContainerSlot"
  ],
  "slotsWhereActive": [
    "UtilitySlot"
  ],
  "activeOnGround": false,
  "destroyedWhenUnequiped": false,
  "forceEquip": false,
  "forceEquipSlot": "",
  "canBeStacked": false,
  "stackSize": 10,
  "defaultStackCount": -1,
  "costs": [
    0,
    4000,
    0,
    0,
    0
  ],
  "itemTags": [
    "Wood"
  ],
  "activeTags": [],
  "inactiveTags": [],
  "magical": true,
  "requiresAttunement": true,
  "requiresIdentification": true,
  "requiredAttunementClasses": [
    "Definition:Bard:8d8eb73e8e6c7d24789c3381ab0acccb"
  ],
  "itemRarity": "Rare",
  "incompatibleWithMonkReturnMissile": false,
  "staticProperties": [],
  "isArmor": false,
  "isWeapon": false,
  "isAmmunition": false,
  "isUsableDevice": true,
  "usableDeviceDescription": {
    "$type": "UsableDeviceDescription, Assembly-CSharp",
    "usage": "Charges",
    "chargesCapital": "Fixed",
    "chargesCapitalNumber": 3,
    "chargesCapitalDie": "D1",
    "chargesCapitalBonus": 0,
    "rechargeRate": "LongRest",
    "rechargeNumber": 3,
    "rechargeDie": "D1",
    "rechargeBonus": 0,
    "outOfChargesConsequence": "Persist",
    "magicAttackBonus": 0,
    "saveDC": 0,
    "deviceFunctions": [
      {
        "$type": "DeviceFunctionDescription, Assembly-CSharp",
        "parentUsage": "Charges",
        "useAffinity": "ChargeCost",
        "useAmount": 1,
        "rechargeRate": "Dawn",
        "durationType": "Hour",
        "canOverchargeSpell": true,
        "type": "Power",
        "spellDefinition": "Definition:HealingWord:0d615e01b2fdf5f42815342ea1e0a26f",
        "featureDefinitionPower": "Definition:PowerFluteOfRespiteSoothingNotes:755aea4d31c7c044cbf9ebd4e12f552b"
      }
    ],
    "usableDeviceTags": [],
    "onUseParticle": {
      "$type": "UnityEngine.AddressableAssets.AssetReference, Unity.Addressables",
      "m_AssetGUID": "",
      "m_SubObjectName": "",
      "m_SubObjectType": ""
    }
  },
  "isTool": false,
  "isMusicalInstrument": true,
  "musicalInstrumentDefinition": {
    "$type": "MusicalInstrumentDescription, Assembly-CSharp",
    "musicalInstrumentType": "WoodwindsType"
  },
  "isStarterPack": false,
  "isContainerItem": false,
  "isLightSourceItem": false,
  "isFocusItem": true,
  "focusItemDefinition": {
    "$type": "FocusItemDescription, Assembly-CSharp",
    "focusType": "MusicalInstrument",
    "shownAsFocus": true
  },
  "isWealthPile": false,
  "isSpellbook": false,
  "isDocument": false,
  "isFood": false,
  "isFactionRelic": false,
  "personalityFlagOccurences": [],
  "soundEffectDescriptionOverride": {
    "$type": "SoundEffectDescription, Assembly-CSharp",
    "startEvent": {
      "$type": "AK.Wwise.Event, AK.Wwise.Unity.API.WwiseTypes",
      "WwiseObjectReference": null,
      "idInternal": 0,
      "valueGuidInternal": {
        "$type": "System.Byte[], mscorlib",
        "$value": ""
      }
    },
    "stopEvent": {
      "$type": "AK.Wwise.Event, AK.Wwise.Unity.API.WwiseTypes",
      "WwiseObjectReference": null,
      "idInternal": 0,
      "valueGuidInternal": {
        "$type": "System.Byte[], mscorlib",
        "$value": ""
      }
    },
    "startSwitch": {
      "$type": "AK.Wwise.Switch, AK.Wwise.Unity.API.WwiseTypes",
      "WwiseObjectReference": {
        "$type": "WwiseSwitchReference, AK.Wwise.Unity.API.WwiseTypes",
        "WwiseSwitchGroupReference": {
          "$type": "WwiseSwitchGroupReference, AK.Wwise.Unity.API.WwiseTypes",
          "objectName": "Switch_MusicalInstruments",
          "id": 4116248476,
          "guid": "5FCBDCDE-A350-4265-831C-7EF02F26DC76",
          "name": "5FCBDCDE-A350-4265-831C-7EF02F26DC76"
        },
        "objectName": "WW_Flute",
        "id": 2999278480,
        "guid": "7FEB4C5C-702C-4610-9ABD-D10F7113F5A5",
        "name": "7FEB4C5C-702C-4610-9ABD-D10F7113F5A5"
      },
      "groupIdInternal": 0,
      "groupGuidInternal": {
        "$type": "System.Byte[], mscorlib",
        "$value": ""
      },
      "idInternal": 0,
      "valueGuidInternal": {
        "$type": "System.Byte[], mscorlib",
        "$value": ""
      }
    },
    "stopSwitch": {
      "$type": "AK.Wwise.Switch, AK.Wwise.Unity.API.WwiseTypes",
      "WwiseObjectReference": null,
      "groupIdInternal": 0,
      "groupGuidInternal": {
        "$type": "System.Byte[], mscorlib",
        "$value": ""
      },
      "idInternal": 0,
      "valueGuidInternal": {
        "$type": "System.Byte[], mscorlib",
        "$value": ""
      }
    },
    "guiStoreBody": {
      "$type": "AK.Wwise.Event, AK.Wwise.Unity.API.WwiseTypes",
      "WwiseObjectReference": null,
      "idInternal": 0,
      "valueGuidInternal": {
        "$type": "System.Byte[], mscorlib",
        "$value": ""
      }
    },
    "guiPickBody": {
      "$type": "AK.Wwise.Event, AK.Wwise.Unity.API.WwiseTypes",
      "WwiseObjectReference": null,
      "idInternal": 0,
      "valueGuidInternal": {
        "$type": "System.Byte[], mscorlib",
        "$value": ""
      }
    },
    "guiStoreOther": {
      "$type": "AK.Wwise.Event, AK.Wwise.Unity.API.WwiseTypes",
      "WwiseObjectReference": null,
      "idInternal": 0,
      "valueGuidInternal": {
        "$type": "System.Byte[], mscorlib",
        "$value": ""
      }
    },
    "guiPickOther": {
      "$type": "AK.Wwise.Event, AK.Wwise.Unity.API.WwiseTypes",
      "WwiseObjectReference": null,
      "idInternal": 0,
      "valueGuidInternal": {
        "$type": "System.Byte[], mscorlib",
        "$value": ""
      }
    }
  },
  "soundEffectOnHitDescriptionOverride": {
    "$type": "SoundEffectOnHitDescription, Assembly-CSharp",
    "switchOnHit": {
      "$type": "AK.Wwise.Switch, AK.Wwise.Unity.API.WwiseTypes",
      "WwiseObjectReference": null,
      "groupIdInternal": 0,
      "groupGuidInternal": {
        "$type": "System.Byte[], mscorlib",
        "$value": ""
      },
      "idInternal": 0,
      "valueGuidInternal": {
        "$type": "System.Byte[], mscorlib",
        "$value": ""
      }
    }
  },
  "itemPresentation": {
    "$type": "ItemPresentation, Assembly-CSharp",
    "unidentifiedTitle": "Equipment/&FluteOfRespiteUnidentifiedTitle",
    "unidentifiedDescription": "Equipment/&FluteOfRespiteUnidentifiedDescription",
    "overrideSubtype": "None",
    "assetReference": {
      "$type": "UnityEngine.AddressableAssets.AssetReference, Unity.Addressables",
      "m_AssetGUID": "b22c4c2e758689447a1f2ff7b8dc84a3",
      "m_SubObjectName": "",
      "m_SubObjectType": ""
    },
    "scaleFactorWhileWielded": 1.0,
    "useArmorAddressableName": false,
    "isArmorAddressableNameGenderSpecific": false,
    "armorAddressableName": "",
    "maleArmorAddressableName": "",
    "femaleArmorAddressableName": "",
    "useCustomArmorMaterial": false,
    "customArmorMaterial": "",
    "ignoreCustomArmorMaterialOnCommonClothes": false,
    "hasCrownVariationMask": false,
    "crownVariationMask": 0,
    "sameBehavioursForMaleAndFemale": true,
    "maleBodyPartBehaviours": [],
    "femaleBodyPartBehaviours": [],
    "itemFlags": [],
    "serializedVersion": 1
  },
  "clueSuspectPairs": [],
  "guiPresentation": {
    "$type": "GuiPresentation, Assembly-CSharp",
    "hidden": false,
    "title": "Equipment/&FluteOfRespiteTitle",
    "description": "Equipment/&FluteOfRespiteDescription",
    "spriteReference": {
      "$type": "UnityEngine.AddressableAssets.AssetReferenceSprite, Unity.Addressables",
      "m_AssetGUID": "ae71fcfd7d180974dbff3bc73d4290ac",
      "m_SubObjectName": "DLC2.5-FluteOfRespite",
      "m_SubObjectType": "UnityEngine.Sprite, UnityEngine.CoreModule, Version=0.0.0.0, Culture=neutral, PublicKeyToken=null"
    },
    "color": {
      "$type": "UnityEngine.Color, UnityEngine.CoreModule",
      "r": 1.0,
      "g": 1.0,
      "b": 1.0,
      "a": 1.0
    },
    "symbolChar": "221E",
    "sortOrder": 0,
    "unusedInSolastaCOTM": false,
    "usedInValleyDLC": false
  },
  "contentCopyright": "TacticalAdventuresContent",
  "guid": "e59c364d36281434b94e7b4cce6690ce",
  "contentPack": "BaseGame",
  "name": "FluteOfRespite"
}