{
  "$type": "MorphotypeElementDefinition, Assembly-CSharp",
  "playerSelectable": true,
  "category": "BodyDecorationColor",
  "mainColor": {
    "$type": "UnityEngine.Color, UnityEngine.CoreModule",
    "r": 1.05927372,
    "g": 0.0,
    "b": 0.42703706,
    "a": 1.0
  },
  "secondColor": {
    "$type": "UnityEngine.Color, UnityEngine.CoreModule",
    "r": 1.0,
    "g": 1.0,
    "b": 1.0,
    "a": 1.0
  },
  "thirdColor": {
    "$type": "UnityEngine.Color, UnityEngine.CoreModule",
    "r": 1.0,
    "g": 1.0,
    "b": 1.0,
    "a": 1.0
  },
  "replaceEyeColorMask": false,
  "bodyDecorationType": "Tattoo",
  "bodyDecorationBlendFactor": 1.0,
  "minMaxValue": {
    "$type": "TA.RangedFloat, Assembly-CSharp",
    "minValue": 0.0,
    "maxValue": 100.0
  },
  "originAllowed": [
    "Origin_NonHuman",
    "Origin_AF",
    "Origin_AS",
    "Origin_CA",
    "Origin_HO",
    "Origin_Dragonborn"
  ],
  "subClassFilterMask": "SorcererManaPainter",
  "forbiddenWithFaceshapes": [],
  "guiPresentation": {
    "$type": "GuiPresentation, Assembly-CSharp",
    "hidden": false,
    "title": "Feature/&NoContentTitle",
    "description": "Feature/&NoContentTitle",
    "spriteReference": {
      "$type": "UnityEngine.AddressableAssets.AssetReferenceSprite, Unity.Addressables",
      "m_AssetGUID": "",
      "m_SubObjectName": "",
      "m_SubObjectType": ""
    },
    "color": {
      "$type": "UnityEngine.Color, UnityEngine.CoreModule",
      "r": 1.0,
      "g": 0.0,
      "b": 0.4000001,
      "a": 1.0
    },
    "symbolChar": "221E",
    "sortOrder": 115,
    "unusedInSolastaCOTM": false,
    "usedInValleyDLC": false
  },
  "contentCopyright": "TacticalAdventuresContent",
  "guid": "38f1a2b97b46e894ea8f5faf4e8b0212",
  "contentPack": "BaseGame",
  "name": "BodyDecorationColor_SorcererManaPainter_15"
}