{
  "$type": "CharacterSubclassDefinition, Assembly-CSharp",
  "featureUnlocks": [
    {
      "$type": "FeatureUnlockByLevel, Assembly-CSharp",
      "featureDefinition": "Definition:PowerCollegeOfThespianCombatInspiration:ea89891e-c189-5ba9-8a5c-33cfcf0d11cd",
      "level": 3
    },
    {
      "$type": "FeatureUnlockByLevel, Assembly-CSharp",
      "featureDefinition": "Definition:MagicAffinityCollegeOfThespianMacabreInstruments:5c22f23c-c911-5bd6-8489-3908c4c5f290",
      "level": 3
    },
    {
      "$type": "FeatureUnlockByLevel, Assembly-CSharp",
      "featureDefinition": "Definition:PowerCollegeOfThespianTerrificPerformance:ed5f8e89-7ca7-59ee-bd76-b9f936d0797a",
      "level": 3
    },
    {
      "$type": "FeatureUnlockByLevel, Assembly-CSharp",
      "featureDefinition": "Definition:ProficiencyCollegeOfThespianFightingStyle:6db1feee-9ed0-5c15-b85d-9c8088a7d884",
      "level": 3
    },
    {
      "$type": "FeatureUnlockByLevel, Assembly-CSharp",
      "featureDefinition": "Definition:AttributeModifierCasterFightingExtraAttack:d683c90c-1240-51bc-878a-617aa7133df0",
      "level": 6
    },
    {
      "$type": "FeatureUnlockByLevel, Assembly-CSharp",
      "featureDefinition": "Definition:PowerCollegeOfThespianFinale:43ce8d9d-89bf-5f3a-83be-54480c9389d0",
      "level": 6
    },
    {
      "$type": "FeatureUnlockByLevel, Assembly-CSharp",
      "featureDefinition": "Definition:PowerCollegeOfThespianImprovedTerrificPerformance:d19392a6-f6b2-566d-921a-9b12abbb06d4",
      "level": 14
    }
  ],
  "personalityFlagOccurences": [],
  "morphotypeSubclassFilterTag": "Default",
  "guiPresentation": {
    "$type": "GuiPresentation, Assembly-CSharp",
    "hidden": false,
    "title": "Subclass/&CollegeOfThespianTitle",
    "description": "Subclass/&CollegeOfThespianDescription",
    "spriteReference": {
      "$type": "UnityEngine.AddressableAssets.AssetReferenceSprite, Unity.Addressables",
      "m_AssetGUID": "fe138214-f7ad-5f41-bd49-65739041f942",
      "m_SubObjectName": null,
      "m_SubObjectType": null
    },
    "color": {
      "$type": "UnityEngine.Color, UnityEngine.CoreModule",
      "r": 1.0,
      "g": 1.0,
      "b": 1.0,
      "a": 1.0
    },
    "symbolChar": "221E",
    "sortOrder": 0,
    "unusedInSolastaCOTM": false,
    "usedInValleyDLC": false
  },
  "contentCopyright": "UserContent",
  "guid": "21ef12f6-061c-58a4-a072-9b74849bf53d",
  "contentPack": 9999,
  "name": "CollegeOfThespian"
}