{
  "$type": "CharacterSubclassDefinition, Assembly-CSharp",
  "featureUnlocks": [
    {
      "$type": "FeatureUnlockByLevel, Assembly-CSharp",
      "featureDefinition": "Definition:MagicAffinitySoulBladeExpandedSpells:3ccab35a-8074-5d5e-b5ab-4f278f9f5fd2",
      "level": 1
    },
    {
      "$type": "FeatureUnlockByLevel, Assembly-CSharp",
      "featureDefinition": "Definition:ProficiencySoulBladeArmor:4778a605-86e3-599a-b627-6077d32a5a55",
      "level": 1
    },
    {
      "$type": "FeatureUnlockByLevel, Assembly-CSharp",
      "featureDefinition": "Definition:ProficiencySoulBladeWeapon:9f57a0aa-dfaf-5d9c-8890-ab3cd681560b",
      "level": 1
    },
    {
      "$type": "FeatureUnlockByLevel, Assembly-CSharp",
      "featureDefinition": "Definition:PowerSoulBladeEmpowerWeapon:f0387894-e020-5e52-92d5-f5b88bb6997d",
      "level": 1
    },
    {
      "$type": "FeatureUnlockByLevel, Assembly-CSharp",
      "featureDefinition": "Definition:PowerSoulBladeSummonPactWeapon:eb40dd01-76b3-57d1-9d3a-243eef28250a",
      "level": 6
    },
    {
      "$type": "FeatureUnlockByLevel, Assembly-CSharp",
      "featureDefinition": "Definition:PowerSoulBladeSoulShield:66b84def-ee8c-59de-bf91-055011cf192b",
      "level": 10
    }
  ],
  "personalityFlagOccurences": [],
  "morphotypeSubclassFilterTag": "Default",
  "guiPresentation": {
    "$type": "GuiPresentation, Assembly-CSharp",
    "hidden": false,
    "title": "Subclass/&PatronSoulBladeTitle",
    "description": "Subclass/&PatronSoulBladeDescription",
    "spriteReference": {
      "$type": "UnityEngine.AddressableAssets.AssetReferenceSprite, Unity.Addressables",
      "m_AssetGUID": "0850c648d07d8b44b8a07c6562372816",
      "m_SubObjectName": "Paladin_Oath_Of_The_Motherland",
      "m_SubObjectType": "UnityEngine.Sprite, UnityEngine.CoreModule, Version=0.0.0.0, Culture=neutral, PublicKeyToken=null"
    },
    "color": {
      "$type": "UnityEngine.Color, UnityEngine.CoreModule",
      "r": 1.0,
      "g": 1.0,
      "b": 1.0,
      "a": 1.0
    },
    "symbolChar": "221E",
    "sortOrder": 0,
    "unusedInSolastaCOTM": false,
    "usedInValleyDLC": false
  },
  "contentCopyright": "UserContent",
  "guid": "f67b75b9-d492-5b53-aae2-4a910e107db2",
  "contentPack": 9999,
  "name": "PatronSoulBlade"
}