{
  "$type": "BlueprintCategory, Assembly-CSharp",
  "guiPresentation": {
    "$id": "1",
    "$type": "GuiPresentation, Assembly-CSharp",
    "hidden": false,
    "title": "Ornaments Necropolis<color=yellow> [MODDED]</color>",
    "description": "Feature/&NoContentTitle",
    "spriteReference": {
      "$id": "2",
      "$type": "UnityEngine.AddressableAssets.AssetReferenceSprite, Unity.Addressables",
      "m_AssetGUID": "",
      "m_SubObjectName": "",
      "m_SubObjectType": ""
    },
    "color": {
      "$id": "3",
      "$type": "UnityEngine.Color, UnityEngine.CoreModule",
      "r": 1.0,
      "g": 1.0,
      "b": 1.0,
      "a": 1.0
    },
    "symbolChar": "221E",
    "sortOrder": 13,
    "unusedInSolastaCOTM": false
  },
  "contentCopyright": "OpenGameContent",
  "guid": "7c87dd93-9bd0-507d-81f9-f5616d6ba62b",
  "contentPack": "BaseGame",
  "name": "Ornaments~Necropolis~MOD"
}