{
  "$type": "PropBlueprint, Assembly-CSharp",
  "groundPlacement": true,
  "groundLowPlacement": false,
  "groundHighPlacement": false,
  "wallPlacement": false,
  "openingPlacement": true,
  "openingLowPlacement": false,
  "openingHighPlacement": false,
  "propPlacement": false,
  "lightSources": [],
  "category": "Partitions",
  "dimensions": {
    "$type": "UnityEngine.Vector2Int, UnityEngine.CoreModule"
  },
  "prefabsByEnvironment": [
    {
      "$type": "BaseBlueprint+PrefabByEnvironmentDescription, Assembly-CSharp",
      "environment": "Necropolis",
      "prefabReference": {
        "$type": "UnityEngine.AddressableAssets.AssetReference, Unity.Addressables",
        "m_AssetGUID": "40986f7dfa452544b90683c06a56302f",
        "m_SubObjectName": "",
        "m_SubObjectType": ""
      }
    },
    {
      "$type": "BaseBlueprint+PrefabByEnvironmentDescription, Assembly-CSharp",
      "environment": "Stronghold",
      "prefabReference": {
        "$type": "UnityEngine.AddressableAssets.AssetReference, Unity.Addressables",
        "m_AssetGUID": "7161cf1f582dae3458ac1d2996e02fc7",
        "m_SubObjectName": "",
        "m_SubObjectType": ""
      }
    },
    {
      "$type": "BaseBlueprint+PrefabByEnvironmentDescription, Assembly-CSharp",
      "environment": "ElvenPalace",
      "prefabReference": {
        "$type": "UnityEngine.AddressableAssets.AssetReference, Unity.Addressables",
        "m_AssetGUID": "1be4de2c17136bf4cbfe0cbc5c6e2e2e",
        "m_SubObjectName": "",
        "m_SubObjectType": ""
      }
    },
    {
      "$type": "BaseBlueprint+PrefabByEnvironmentDescription, Assembly-CSharp",
      "environment": "LavaCaves",
      "prefabReference": {
        "$type": "UnityEngine.AddressableAssets.AssetReference, Unity.Addressables",
        "m_AssetGUID": "d9116aa986675ed4aa7d20cfa223c665",
        "m_SubObjectName": "",
        "m_SubObjectType": ""
      }
    },
    {
      "$type": "BaseBlueprint+PrefabByEnvironmentDescription, Assembly-CSharp",
      "environment": "Sewers",
      "prefabReference": {
        "$type": "UnityEngine.AddressableAssets.AssetReference, Unity.Addressables",
        "m_AssetGUID": "7f9f2ce61c8ac614cbde805e310e6f63",
        "m_SubObjectName": "",
        "m_SubObjectType": ""
      }
    },
    {
      "$type": "BaseBlueprint+PrefabByEnvironmentDescription, Assembly-CSharp",
      "environment": "Catacombs",
      "prefabReference": {
        "$type": "UnityEngine.AddressableAssets.AssetReference, Unity.Addressables",
        "m_AssetGUID": "32fccf6c918b772438d1f52d4c3e07d7",
        "m_SubObjectName": "",
        "m_SubObjectType": ""
      }
    },
    {
      "$type": "BaseBlueprint+PrefabByEnvironmentDescription, Assembly-CSharp",
      "environment": "ValleyPalace",
      "prefabReference": {
        "$type": "UnityEngine.AddressableAssets.AssetReference, Unity.Addressables",
        "m_AssetGUID": "1a914d2bbea19f34ebb342335e141419",
        "m_SubObjectName": "",
        "m_SubObjectType": ""
      }
    }
  ],
  "guiPresentation": {
    "$type": "GuiPresentation, Assembly-CSharp",
    "hidden": false,
    "title": "Prop/&WallSimpleTitle",
    "description": "",
    "spriteReference": {
      "$type": "UnityEngine.AddressableAssets.AssetReferenceSprite, Unity.Addressables",
      "m_AssetGUID": "84a42c28c4b2f9042a42833a41b463c5",
      "m_SubObjectName": "WallBlocker",
      "m_SubObjectType": ""
    },
    "color": {
      "$type": "UnityEngine.Color, UnityEngine.CoreModule",
      "r": 1.0,
      "g": 1.0,
      "b": 1.0,
      "a": 1.0
    },
    "symbolChar": "221E",
    "sortOrder": 2,
    "unusedInSolastaCOTM": false,
    "usedInValleyDLC": false
  },
  "contentCopyright": "OpenGameContent",
  "guid": "e9edb6ba07ffc7146b231df398e53705",
  "contentPack": "BaseGame",
  "name": "Wall_Simple_B"
}