{
  "$type": "RecipeDefinition, Assembly-CSharp",
  "craftedItem": "Definition:Enchanted_Javelin_Souldrinker:6860470d-4c92-5a44-b112-0898d0a46da6",
  "stackCount": 3,
  "craftingHours": 48,
  "craftingDC": 16,
  "toolTypeDefinition": "Definition:EnchantingToolType:9565acf734ebd0d4e90a6ba75091887d",
  "ingredients": [
    {
      "$type": "IngredientOccurenceDescription, Assembly-CSharp",
      "amount": 1,
      "itemDefinition": "Definition:Javelin:b4580025f1f488a489f151cc9ae45118"
    },
    {
      "$type": "IngredientOccurenceDescription, Assembly-CSharp",
      "amount": 1,
      "itemDefinition": "Definition:Ingredient_Enchant_Soul_Gem:21ac94fc3ec649b4ba9b6a8bc46b4c77"
    }
  ],
  "spellDefinition": null,
  "guiPresentation": {
    "$type": "GuiPresentation, Assembly-CSharp",
    "hidden": false,
    "title": "Equipment/&Enchanted_Javelin_Souldrinker_Title",
    "description": "Equipment/&Enchanted_Javelin_Souldrinker_Description",
    "spriteReference": {
      "$type": "UnityEngine.AddressableAssets.AssetReferenceSprite, Unity.Addressables",
      "m_AssetGUID": "3fecf647c6a83564184546928f428a51",
      "m_SubObjectName": "StandardJavelin",
      "m_SubObjectType": "UnityEngine.Sprite, UnityEngine.CoreModule, Version=0.0.0.0, Culture=neutral, PublicKeyToken=null"
    },
    "color": {
      "$type": "UnityEngine.Color, UnityEngine.CoreModule",
      "r": 1.0,
      "g": 1.0,
      "b": 1.0,
      "a": 1.0
    },
    "symbolChar": "221E",
    "sortOrder": 0,
    "unusedInSolastaCOTM": false,
    "usedInValleyDLC": false
  },
  "contentCopyright": "UserContent",
  "guid": "c1937dd0-34b0-5a7b-9422-5b916674742b",
  "contentPack": 9999,
  "name": "RecipeEnchantingEnchanted_Javelin_Souldrinker"
}