{
  "$type": "SolastaUnfinishedBusiness.CustomDefinitions.FeatDefinitionWithPrerequisites, SolastaUnfinishedBusiness",
  "compatibleClassesPrerequisite": [],
  "mustCastSpellsPrerequisite": true,
  "compatibleRacesPrerequisite": [],
  "minimalAbilityScorePrerequisite": false,
  "minimalAbilityScoreValue": 13,
  "minimalAbilityScoreName": "Strength",
  "armorProficiencyPrerequisite": false,
  "armorProficiencyCategory": "",
  "hasFamilyTag": false,
  "familyTag": "",
  "knownFeatsPrerequisite": [],
  "features": [
    "Definition:PointPoolFeatMagicInitiateWizard:1ac73f74-0a26-5885-9764-c9df095c5338"
  ],
  "guiPresentation": {
    "$type": "GuiPresentation, Assembly-CSharp",
    "hidden": true,
    "title": "Magic Initiate [Wizard]",
    "description": "You learn two cantrips of your choice from the Wizard class's spell list. In addition, choose one 1st-level spell to learn from that same list.",
    "spriteReference": {
      "$type": "UnityEngine.AddressableAssets.AssetReferenceSprite, Unity.Addressables",
      "m_AssetGUID": "",
      "m_SubObjectName": null,
      "m_SubObjectType": null
    },
    "color": {
      "$type": "UnityEngine.Color, UnityEngine.CoreModule",
      "r": 1.0,
      "g": 1.0,
      "b": 1.0,
      "a": 1.0
    },
    "symbolChar": "221E",
    "sortOrder": 0,
    "unusedInSolastaCOTM": false,
    "usedInValleyDLC": false
  },
  "contentCopyright": "UserContent",
  "guid": "5c8dc78a-288b-5544-be4c-fe8bf14d4143",
  "contentPack": 9999,
  "name": "FeatMagicInitiateWizard"
}