{
  "$type": "EncounterDefinition, Assembly-CSharp",
  "dungeonMakerPresence": true,
  "type": "Battle",
  "challengeRating": 9,
  "locationOverride": null,
  "locationBlacklist": [],
  "monsterOccurences": [
    {
      "$type": "MonsterOccurenceDescription, Assembly-CSharp",
      "monsterDefinition": "Definition:TundraTiger_MonsterDefinition:f9015700a865c1145a7ecd91ce4afae7",
      "number": 4,
      "encounterPlacementDecision": "Definition:EncounterSpawn_Spread:4fbd444af01e4f94e8155bc494305192",
      "creatureSex": "Male",
      "presentationDefinitionIndex": 0,
      "randomHumanoidPresentation": false,
      "overrideFaction": false,
      "factionName": ""
    }
  ],
  "guiPresentation": {
    "$type": "GuiPresentation, Assembly-CSharp",
    "hidden": false,
    "title": "Encounter/&DLC3_CR9_TundraTigers_Title",
    "description": "Encounter/&DLC3_CR9_TigerDrakes_Wolves_Description",
    "spriteReference": {
      "$type": "UnityEngine.AddressableAssets.AssetReferenceSprite, Unity.Addressables",
      "m_AssetGUID": "",
      "m_SubObjectName": "",
      "m_SubObjectType": ""
    },
    "color": {
      "$type": "UnityEngine.Color, UnityEngine.CoreModule",
      "r": 1.0,
      "g": 1.0,
      "b": 1.0,
      "a": 1.0
    },
    "symbolChar": "221E",
    "sortOrder": 0,
    "unusedInSolastaCOTM": false,
    "usedInValleyDLC": false
  },
  "contentCopyright": "OpenGameContent",
  "guid": "69e65507da57a0e4aaed1933b37de748",
  "contentPack": "PalaceOfIce",
  "name": "CR9_DLC3_TundraTigers"
}