{
  "$type": "InvocationDefinitionCustom, SolastaUnfinishedBusiness",
  "requiredKnownSpell": null,
  "requiredLevel": 1,
  "requiredPact": null,
  "grantedFeature": "Definition:ProficiencyFeatWeaponMasterMaulType:f0238d7e-05d9-5c23-8c0f-007081025f90",
  "grantedSpell": null,
  "consumesSpellSlot": false,
  "longRestRecharge": false,
  "overrideMaterialComponent": true,
  "guiPresentation": {
    "$type": "GuiPresentation, Assembly-CSharp",
    "hidden": false,
    "title": "Equipment/&MaulTypeTitle",
    "description": "Feature/&NoContentTitle",
    "spriteReference": {
      "$type": "UnityEngine.AddressableAssets.AssetReferenceSprite, Unity.Addressables",
      "m_AssetGUID": "042d55f3ddd9cc448a90daa3bf66ed35",
      "m_SubObjectName": "StandardMaul",
      "m_SubObjectType": "UnityEngine.Sprite, UnityEngine.CoreModule, Version=0.0.0.0, Culture=neutral, PublicKeyToken=null"
    },
    "color": {
      "$type": "UnityEngine.Color, UnityEngine.CoreModule",
      "r": 1.0,
      "g": 1.0,
      "b": 1.0,
      "a": 1.0
    },
    "symbolChar": "221E",
    "sortOrder": 0,
    "unusedInSolastaCOTM": false,
    "usedInValleyDLC": false
  },
  "contentCopyright": "UserContent",
  "guid": "fde1ed8b-cad8-52cc-87f6-ba8443199faa",
  "contentPack": 9999,
  "name": "CustomInvocationFeatWeaponMasterMaulType"
}