{
  "$type": "RecipeDefinition, Assembly-CSharp",
  "dungeonMakerPresence": true,
  "craftedItem": "Definition:ScrollTongues:dba183b613100194f9b308eea722771b",
  "stackCount": 1,
  "craftingHours": 3,
  "craftingDC": 16,
  "toolTypeDefinition": "Definition:ScrollKitType:33c029d33932a7a46a67d5279d181179",
  "ingredients": [
    {
      "$type": "IngredientOccurenceDescription, Assembly-CSharp",
      "amount": 1,
      "itemDefinition": "Definition:100_GP_Emerald:6443e653f20e0164bac3c82feeec49ae"
    },
    {
      "$type": "IngredientOccurenceDescription, Assembly-CSharp",
      "amount": 1,
      "itemDefinition": "Definition:Ingredient_Dragonrose:e6aefc7519b006e489091c77fbca530c"
    },
    {
      "$type": "IngredientOccurenceDescription, Assembly-CSharp",
      "amount": 1,
      "itemDefinition": "Definition:Ingredient_StormHeather:a2365d0b9d4abfd4aba0f048b78c15ff"
    },
    {
      "$type": "IngredientOccurenceDescription, Assembly-CSharp",
      "amount": 1,
      "itemDefinition": "Definition:Ingredient_GoblinHairFungus:80cf95eb060947a4eadc3aa64dcd59c2"
    }
  ],
  "spellDefinition": "Definition:Tongues:fa71b90885b308f4b8998d433c9e41e8",
  "guiPresentation": {
    "$type": "GuiPresentation, Assembly-CSharp",
    "hidden": false,
    "title": "Equipment/&ScrollTonguesTitle",
    "description": "Feature/&NoContentTitle",
    "spriteReference": {
      "$type": "UnityEngine.AddressableAssets.AssetReferenceSprite, Unity.Addressables",
      "m_AssetGUID": "",
      "m_SubObjectName": "",
      "m_SubObjectType": ""
    },
    "color": {
      "$type": "UnityEngine.Color, UnityEngine.CoreModule",
      "r": 1.0,
      "g": 1.0,
      "b": 1.0,
      "a": 1.0
    },
    "symbolChar": "221E",
    "sortOrder": 0,
    "unusedInSolastaCOTM": false,
    "usedInValleyDLC": false
  },
  "contentCopyright": "OpenGameContent",
  "guid": "52b1065c6de025a47a2f47d8eaa5b26b",
  "contentPack": "BaseGame",
  "name": "RecipeScroll_L3_OfTongues"
}